pywulai/__init__.py
pywulai/aibot.py
pywulai/data.py
pywulai/deeplearn.py
pywulai/dialog.py
pywulai/global.py
pywulai/kmbase.py
pywulai/kms.py
pywulai/model.py
pywulai/multiple.py
pywulai/nlp.py
pywulai/plan.py
pywulai/schedule.py
pywulai/task.py
pywulai-1.2.0.dist-info/LICENSE
pywulai-1.2.0.dist-info/METADATA
pywulai-1.2.0.dist-info/WHEEL
pywulai-1.2.0.dist-info/top_level.txt
pywulai-1.2.0.dist-info/RECORD
